apigateway/__version__.py
apigateway/core/__init__.py
apigateway/core/adapters/__init__.py
apigateway/core/adapters/base_adapter.py
apigateway/core/adapters/django.py
apigateway/core/adapters/fastapi.py
apigateway/core/adapters/flask.py
apigateway/core/adapters/generic.py
apigateway/core/auth/__init__.py
apigateway/core/auth/auth.py
apigateway/core/enums/__init__.py
apigateway/core/enums/validation_modes.py
apigateway/core/errors/__init.py
apigateway/core/errors/formatters.py
apigateway/core/logging/__init__.py
apigateway/core/logging/abstract_logger.py
apigateway/core/logging/context.py
apigateway/core/logging/json_logger.py
apigateway/core/logging/logger.py
apigateway/core/logging/manager.py
apigateway/core/rate_limit/MemoryBackend.py
apigateway/core/rate_limit/RateLimitEngine.py
apigateway/core/rate_limit/RateLimiting.py
apigateway/core/rate_limit/RedisBackend.py
apigateway/core/rate_limit/__init__.py
apigateway/core/rate_limit/rateLimitAbstractBackend.py
apigateway/core/rate_limit/rate_limit_middleware.py
apigateway/core/validation/__init__.py
apigateway/core/validation/file_validation.py
apigateway/core/validation/validation.py
apigateway/exceptions/AuthError.py
apigateway/exceptions/GatewayValidationError.py
apigateway/exceptions/RateLimitError.py
apigateway/exceptions/__init__.py
apigatewaybuilder-1.4.1.dist-info/licenses/LICENSE
apigatewaybuilder-1.4.1.dist-info/METADATA
apigatewaybuilder-1.4.1.dist-info/WHEEL
apigatewaybuilder-1.4.1.dist-info/top_level.txt
apigatewaybuilder-1.4.1.dist-info/RECORD
