Metadata-Version: 2.4
Name: apigatewaybuilder
Version: 1.4.1
Summary: Framework-agnostic API Gateway with validation, auth, and rate limiting
Author: PrabhBirJ
License: MIT
Project-URL: Homepage, https://github.com/PrabhBirJ/apigateway
Project-URL: Documentation, https://github.com/PrabhBirJ/apigateway#readme
Project-URL: Repository, https://github.com/PrabhBirJ/apigateway
Project-URL: Issues, https://github.com/PrabhBirJ/apigateway/issues
Keywords: api,gateway,validation,authorization,rate-limiting
Classifier: Development Status :: 4 - Beta
Classifier: Intended Audience :: Developers
Classifier: License :: OSI Approved :: MIT License
Classifier: Programming Language :: Python :: 3.11
Classifier: Programming Language :: Python :: 3.12
Classifier: Framework :: Django
Classifier: Framework :: Flask
Classifier: Framework :: FastAPI
Requires-Python: >=3.11
License-File: LICENSE
Requires-Dist: pydantic>=2.11.0
Requires-Dist: pyjwt>=2.8.0
Provides-Extra: flask
Requires-Dist: flask>=3.0.0; extra == "flask"
Requires-Dist: flask-cors>=4.0.0; extra == "flask"
Provides-Extra: django
Requires-Dist: django>=4.2.0; extra == "django"
Provides-Extra: fastapi
Requires-Dist: fastapi>=0.100.0; extra == "fastapi"
Requires-Dist: uvicorn[standard]>=0.25.0; extra == "fastapi"
Provides-Extra: redis
Requires-Dist: redis>=5.0.0; extra == "redis"
Provides-Extra: all
Requires-Dist: apigateway[django,fastapi,flask,redis]; extra == "all"
Provides-Extra: dev
Requires-Dist: pytest>=8.0.0; extra == "dev"
Requires-Dist: pytest-asyncio>=0.24.0; extra == "dev"
Requires-Dist: pytest-cov>=5.0.0; extra == "dev"
Requires-Dist: pytest-django>=4.8.0; extra == "dev"
Requires-Dist: httpx>=0.25.0; extra == "dev"
Requires-Dist: black>=24.0.0; extra == "dev"
Requires-Dist: ruff>=0.1.0; extra == "dev"
Requires-Dist: mypy>=1.8.0; extra == "dev"
Provides-Extra: test
Requires-Dist: pytest>=8.0.0; extra == "test"
Requires-Dist: pytest-asyncio>=0.24.0; extra == "test"
Requires-Dist: pytest-cov>=5.0.0; extra == "test"
Requires-Dist: pytest-django>=4.8.0; extra == "test"
Requires-Dist: httpx>=0.25.0; extra == "test"
Dynamic: license-file
